CHANGELOG.txt
LICENCE.txt
MANIFEST.in
README.txt
setup.py
funcad/__init__.py
funcad/funcad.py
funcad.egg-info/PKG-INFO
funcad.egg-info/SOURCES.txt
funcad.egg-info/dependency_links.txt
funcad.egg-info/requires.txt
funcad.egg-info/top_level.txt