Metadata-Version: 2.1
Name: funcad
Version: 0.0.1.3
Summary: python functions for robotics
Home-page: https://robocadv.readthedocs.io/en/latest/docs/all_docs/funcad_docs/index.html
Author: Abdrakov Airat
Author-email: abdrakovairat@gmail.com
License: MIT
Keywords: function,robotics
Platform: UNKNOWN
Classifier: Development Status :: 5 - Production/Stable
Classifier: Intended Audience :: Education
Classifier: Operating System :: Microsoft :: Windows :: Windows 10
Classifier: License :: OSI Approved :: MIT License
Classifier: Programming Language :: Python :: 3
License-File: LICENCE.txt
